[ {
  "name" : "Wind Van Gogh 2100",
  "link" : "https://www.gsmarena.com/wnd_wind_van_gogh_2100-2169.php",
  "imgUrl" : "https://fdn2.gsmarena.com/vv/bigpic/wind-atom-van-gogh.gif",
  "info" : {
    "Technology" : "GSM",
    "2G bands" : "GSM 900 / 1800 / 1900",
    "GPRS" : "Class 10",
    "EDGE" : "No",
    "Announced" : "2007, October",
    "Status" : "Cancelled",
    "Dimensions" : "98 x 47.5 x 16.3 mm (3.86 x 1.87 x 0.64 in)",
    "Weight" : "75 g (2.65 oz)",
    "SIM" : "Mini-SIM",
    "Type" : "Removable Li-Ion 820 mAh battery",
    "Size" : "1.8 inches, 10.2 cm2 (~21.9% screen-to-body ratio)",
    "Resolution" : "176 x 220 pixels (~157 ppi density)",
    " " : "Built-in detachable Bluetooth earpiece\nMP3/AAC player\nMP4/3gp player\nVoice memo\nPredictive text input",
    "Card slot" : "microSD",
    "Phonebook" : "1000 entries, Photocall",
    "Call records" : "50 received, 50 dialed, 50 missed calls",
    "Internal" : "128MB",
    "Single" : "2 MP",
    "Video" : "No",
    "Loudspeaker " : "Yes",
    "Alert types" : "Vibration; Downloadable polyphonic, MIDI, MP3 ringtones",
    "3.5mm jack " : "No",
    "WLAN" : "No",
    "Bluetooth" : "1.2, A2DP",
    "Positioning" : "No",
    "Radio" : "FM radio",
    "USB" : "1.1",
    "Sensors" : "",
    "Messaging" : "SMS, MMS, Email",
    "Browser" : "WAP 2.0/xHTML",
    "Games" : "Yes + downloadable",
    "Java" : "Yes, MIDP 2.0",
    "Stand-by" : "Up to 150 h",
    "Talk time" : "Up to 3 h",
    "Colors" : "Silver-Gray, Silver-Fuchsia"
  },
  "brand" : "WND"
}, {
  "name" : "Wind DUO 2300",
  "link" : "https://www.gsmarena.com/wnd_wind_duo_2300-2168.php",
  "imgUrl" : "https://fdn2.gsmarena.com/vv/bigpic/wind-duo-2300.gif",
  "info" : {
    "Technology" : "GSM",
    "2G bands" : "GSM 900 / 1800 / 1900",
    "GPRS" : "Class 10",
    "EDGE" : "No",
    "Announced" : "2007, October",
    "Status" : "Cancelled",
    "Dimensions" : "99.5 x 47.5 x 18 mm (3.92 x 1.87 x 0.71 in)",
    "Weight" : "120 g (4.23 oz)",
    "SIM" : "Dual SIM (Mini-SIM)",
    "Type" : "Removable Li-Ion 930 mAh battery",
    "Size" : "1.9 inches, 11.2 cm2 (~23.7% screen-to-body ratio)",
    "Resolution" : "240 x 320 pixels, 4:3 ratio (~211 ppi density)",
    " " : "MP3/AAC player\nMP4/3gp player\nVoice memo\nPredictive text input",
    "Card slot" : "microSD on both sides",
    "Phonebook" : "1000 entries on each side, Photocall",
    "Call records" : "20 received, 20 dialed, 20 missed calls",
    "Single" : "2 MP, on each side",
    "Video" : "No",
    "Loudspeaker " : "Yes",
    "Alert types" : "Vibration; Downloadable polyphonic, MIDI, MP3 ringtones",
    "3.5mm jack " : "No",
    "WLAN" : "No",
    "Bluetooth" : "1.2, A2DP",
    "Positioning" : "No",
    "Radio" : "No",
    "USB" : "1.1",
    "Sensors" : "",
    "Messaging" : "SMS, MMS, Email",
    "Browser" : "WAP 2.0/xHTML",
    "Games" : "Yes + downloadable",
    "Java" : "Yes, MIDP 2.0",
    "Stand-by" : "Up to 180 h",
    "Talk time" : "Up to 3 h",
    "Colors" : "White-gold, Yellow-gold"
  },
  "brand" : "WND"
}, {
  "name" : "Wind DUO 2200",
  "link" : "https://www.gsmarena.com/wnd_wind_duo_2200-2166.php",
  "imgUrl" : "https://fdn2.gsmarena.com/vv/bigpic/wind-duo-2200.gif",
  "info" : {
    "Technology" : "GSM",
    "2G bands" : "GSM 900 / 1800 / 1900",
    "GPRS" : "Class 10",
    "EDGE" : "No",
    "Announced" : "2007, October",
    "Status" : "Discontinued",
    "Dimensions" : "98 x 47.5 x 17.3 mm (3.86 x 1.87 x 0.68 in)",
    "Weight" : "95 g (3.35 oz)",
    "SIM" : "Dual SIM (Mini-SIM)",
    "Type" : "Removable Li-Ion 930 mAh battery",
    "Size" : "1.8 inches, 10.0 cm2 (~21.6% screen-to-body ratio)",
    "Resolution" : "240 x 320 pixels, 4:3 ratio (~222 ppi density)",
    " " : "MP3/AAC player\nMP4/3gp player\nVoice memo\nPredictive text input",
    "Card slot" : "microSD (dedicated slot) on both sides",
    "Phonebook" : "1000 entries on each side, Photocall",
    "Call records" : "20 received, 20 dialed, 20 missed calls",
    "Single" : "2 MP, on each side",
    "Video" : "No",
    "Loudspeaker " : "Yes",
    "Alert types" : "Vibration; Downloadable polyphonic, MIDI, MP3 ringtones",
    "3.5mm jack " : "No",
    "WLAN" : "No",
    "Bluetooth" : "1.2, A2DP",
    "Positioning" : "No",
    "Radio" : "No",
    "USB" : "1.1",
    "Sensors" : "",
    "Messaging" : "SMS, MMS, Email",
    "Browser" : "WAP 2.0/xHTML",
    "Games" : "Yes + downloadable",
    "Java" : "Yes, MIDP 2.0",
    "Stand-by" : "Up to 180 h",
    "Talk time" : "Up to 3 h",
    "Colors" : "Black-silver, Gold-silver, Fuschia-silver"
  },
  "brand" : "WND"
}, {
  "name" : "Wind DUO 2100",
  "link" : "https://www.gsmarena.com/wnd_wind_duo_2100-2167.php",
  "imgUrl" : "https://fdn2.gsmarena.com/vv/bigpic/wind-duo-2100.gif",
  "info" : {
    "Technology" : "GSM",
    "2G bands" : "GSM 900 / 1800 / 1900",
    "GPRS" : "Class 10",
    "EDGE" : "No",
    "Announced" : "2007, October",
    "Status" : "Cancelled",
    "Dimensions" : "98 x 47.5 x 17.3 mm (3.86 x 1.87 x 0.68 in)",
    "Weight" : "93 g (3.28 oz)",
    "SIM" : "Dual SIM (Mini-SIM)",
    "Type" : "Removable Li-Ion 930 mAh battery",
    "Size" : "1.8 inches, 10.0 cm2 (~21.6% screen-to-body ratio)",
    "Resolution" : "240 x 320 pixels, 4:3 ratio (~222 ppi density)",
    " " : "MP3/AAC player\nMP4/3gp player\nVoice memo\nPredictive text input",
    "Card slot" : "microSD on both sides",
    "Phonebook" : "1000 entries on each side, Photocall",
    "Call records" : "20 received, 20 dialed, 20 missed calls",
    "Internal" : "128MB",
    "Single" : "2 MP",
    "Video" : "No",
    "Loudspeaker " : "Yes",
    "Alert types" : "Vibration; Downloadable polyphonic, MIDI, MP3 ringtones",
    "3.5mm jack " : "No",
    "WLAN" : "No",
    "Bluetooth" : "1.2, A2DP",
    "Positioning" : "No",
    "Radio" : "No",
    "USB" : "Proprietary",
    "Sensors" : "",
    "Messaging" : "SMS, MMS, Email",
    "Browser" : "WAP 2.0/xHTML",
    "Games" : "Yes + downloadable",
    "Java" : "Yes, MIDP 2.0",
    "Stand-by" : "Up to 180 h",
    "Talk time" : "Up to 3 h",
    "Colors" : "Black, Gray"
  },
  "brand" : "WND"
}, {
  "name" : "Wind DUO 2000",
  "link" : "https://www.gsmarena.com/wnd_wind_duo_2000-2165.php",
  "imgUrl" : "https://fdn2.gsmarena.com/vv/bigpic/wind-duo-2000.gif",
  "info" : {
    "Technology" : "GSM",
    "2G bands" : "GSM 900 / 1800 / 1900",
    "GPRS" : "Class 10",
    "EDGE" : "No",
    "Announced" : "2007, March",
    "Status" : "Discontinued",
    "Dimensions" : "97 x 48 x 17 mm (3.82 x 1.89 x 0.67 in)",
    "Weight" : "100 g (3.53 oz)",
    "SIM" : "Dual SIM (Mini-SIM)",
    "Type" : "Removable Li-Po 1660 mAh battery",
    "Size" : "1.5 inches, 7.1 cm2 (~15.2% screen-to-body ratio)",
    "Resolution" : "128 x 160 pixels (~137 ppi density)",
    " " : "MP3 player\nVoice memo",
    "Card slot" : "No",
    "Phonebook" : "1000 entries each side, Photocall",
    "Call records" : "50 received, 50 dialed, 50 missed calls",
    "Loudspeaker " : "Yes",
    "Alert types" : "Vibration; Downloadable polyphonic, MIDI, MP3 ringtones",
    "3.5mm jack " : "No",
    "WLAN" : "No",
    "Bluetooth" : "1.2",
    "Positioning" : "No",
    "Radio" : "No",
    "USB" : "Proprietary",
    "Sensors" : "",
    "Messaging" : "SMS",
    "Browser" : "WAP 2.0/xHTML",
    "Games" : "Yes + downloadable",
    "Java" : "Yes, MIDP 2.0",
    "Stand-by" : "Up to 160 h",
    "Talk time" : "Up to 3 h",
    "Colors" : "Silver, Black, Dark gray"
  },
  "brand" : "WND"
} ]