[ {
  "name" : "DV80",
  "link" : "https://www.gsmarena.com/xcute_dv80-1495.php",
  "imgUrl" : "https://fdn2.gsmarena.com/vv/bigpic/xcute-dv80.gif",
  "info" : { },
  "brand" : "XCute"
}, {
  "name" : "DV50",
  "link" : "https://www.gsmarena.com/xcute_dv50-1494.php",
  "imgUrl" : "https://fdn2.gsmarena.com/vv/bigpic/xcute-dv50.gif",
  "info" : { },
  "brand" : "XCute"
}, {
  "name" : "DV2",
  "link" : "https://www.gsmarena.com/xcute_dv2-1481.php",
  "imgUrl" : "https://fdn2.gsmarena.com/vv/bigpic/xcute-dv2.gif",
  "info" : { },
  "brand" : "XCute"
}, {
  "name" : "DV1",
  "link" : "https://www.gsmarena.com/xcute_dv1-1480.php",
  "imgUrl" : "https://fdn2.gsmarena.com/vv/bigpic/xcute-dv1.gif",
  "info" : { },
  "brand" : "XCute"
} ]